nonumpy/__init__.py
nonumpy/ema.py
nonumpy/factory.py
nonumpy/filters.py
nonumpy/nonumpy.h
nonumpy/nonumpy_config.h
nonumpy/nonumpy_ema.c
nonumpy/nonumpy_ema.h
nonumpy/nonumpy_filters.c
nonumpy/nonumpy_filters.h
nonumpy-0.1.2.dist-info/LICENSE
nonumpy-0.1.2.dist-info/METADATA
nonumpy-0.1.2.dist-info/WHEEL
nonumpy-0.1.2.dist-info/RECORD
