Metadata-Version: 2.1
Name: nonumpy
Version: 0.1.2
Summary: 
Author: WideOpenTech
Author-email: foss@wideopentech.co.uk
Requires-Python: >=3.8,<4.0
Classifier: License :: OSI Approved :: MIT License
Classifier: Operating System :: OS Independent
Classifier: Programming Language :: Python :: 3
Classifier: Programming Language :: Python :: 3.8
Classifier: Programming Language :: Python :: 3.9
Classifier: Programming Language :: Python :: 3.10
Classifier: Programming Language :: Python :: 3.11
Classifier: Programming Language :: Python :: 3
Requires-Dist: crelm (>=0.0.26a16,<0.0.27)
Requires-Dist: john (>=0.1.1a3,<0.2.0)
